chillax/__init__.py
chillax/core.py
chillax-0.0.11.dist-info/licenses/LICENSE
chillax-0.0.11.dist-info/METADATA
chillax-0.0.11.dist-info/WHEEL
chillax-0.0.11.dist-info/top_level.txt
chillax-0.0.11.dist-info/RECORD
